[
  {
    "inputs": [],
    "stateMutability": "nonpayable",
    "type": "constructor"
  },
  {
    "anonymous": false,
    "inputs": [
      {
        "indexed": true,
        "internalType": "address",
        "name": "bank",
        "type": "address"
      },
      {
        "indexed": false,
        "internalType": "uint256",
        "name": "amount",
        "type": "uint256"
      }
    ],
    "name": "LiquidityInjected",
    "type": "event"
  },
  {
    "anonymous": false,
    "inputs": [
      {
        "indexed": true,
        "internalType": "bytes32",
        "name": "txHash",
        "type": "bytes32"
      },
      {
        "indexed": false,
        "internalType": "address",
        "name": "sender",
        "type": "address"
      },
      {
        "indexed": false,
        "internalType": "address",
        "name": "receiver",
        "type": "address"
      },
      {
        "indexed": false,
        "internalType": "uint256",
        "name": "amount",
        "type": "uint256"
      },
      {
        "indexed": false,
        "internalType": "bytes32",
        "name": "iso20022Hash",
        "type": "bytes32"
      },
      {
        "indexed": false,
        "internalType": "uint8",
        "name": "riskScore",
        "type": "uint8"
      }
    ],
    "name": "SettlementExecuted",
    "type": "event"
  },
  {
    "anonymous": false,
    "inputs": [
      {
        "indexed": true,
        "internalType": "address",
        "name": "settler",
        "type": "address"
      }
    ],
    "name": "SettlerAuthorized",
    "type": "event"
  },
  {
    "anonymous": false,
    "inputs": [
      {
        "indexed": true,
        "internalType": "address",
        "name": "settler",
        "type": "address"
      }
    ],
    "name": "SettlerRevoked",
    "type": "event"
  },
  {
    "inputs": [],
    "name": "admin",
    "outputs": [
      {
        "internalType": "address",
        "name": "",
        "type": "address"
      }
    ],
    "stateMutability": "view",
    "type": "function"
  },
  {
    "inputs": [
      {
        "internalType": "address",
        "name": "settler",
        "type": "address"
      }
    ],
    "name": "authorizeSettler",
    "outputs": [],
    "stateMutability": "nonpayable",
    "type": "function"
  },
  {
    "inputs": [
      {
        "internalType": "address",
        "name": "",
        "type": "address"
      }
    ],
    "name": "authorizedSettlers",
    "outputs": [
      {
        "internalType": "bool",
        "name": "",
        "type": "bool"
      }
    ],
    "stateMutability": "view",
    "type": "function"
  },
  {
    "inputs": [
      {
        "internalType": "address payable",
        "name": "receiver",
        "type": "address"
      },
      {
        "internalType": "bytes32",
        "name": "iso20022Hash",
        "type": "bytes32"
      },
      {
        "internalType": "uint8",
        "name": "riskScore",
        "type": "uint8"
      }
    ],
    "name": "executeAtomicSwap",
    "outputs": [],
    "stateMutability": "payable",
    "type": "function"
  },
  {
    "inputs": [
      {
        "internalType": "address",
        "name": "bank",
        "type": "address"
      }
    ],
    "name": "getNostroBalance",
    "outputs": [
      {
        "internalType": "uint256",
        "name": "",
        "type": "uint256"
      }
    ],
    "stateMutability": "view",
    "type": "function"
  },
  {
    "inputs": [
      {
        "internalType": "bytes32",
        "name": "txHash",
        "type": "bytes32"
      }
    ],
    "name": "getSettlement",
    "outputs": [
      {
        "components": [
          {
            "internalType": "address",
            "name": "sender",
            "type": "address"
          },
          {
            "internalType": "address",
            "name": "receiver",
            "type": "address"
          },
          {
            "internalType": "uint256",
            "name": "amount",
            "type": "uint256"
          },
          {
            "internalType": "bytes32",
            "name": "iso20022Hash",
            "type": "bytes32"
          },
          {
            "internalType": "uint256",
            "name": "timestamp",
            "type": "uint256"
          },
          {
            "internalType": "bool",
            "name": "completed",
            "type": "bool"
          },
          {
            "internalType": "uint8",
            "name": "riskScore",
            "type": "uint8"
          },
          {
            "internalType": "string",
            "name": "currency",
            "type": "string"
          }
        ],
        "internalType": "struct IPTS_Enterprise_Settlement.SettlementRecord",
        "name": "",
        "type": "tuple"
      }
    ],
    "stateMutability": "view",
    "type": "function"
  },
  {
    "inputs": [],
    "name": "getStats",
    "outputs": [
      {
        "internalType": "uint256",
        "name": "_totalSettlements",
        "type": "uint256"
      },
      {
        "internalType": "uint256",
        "name": "_totalVolume",
        "type": "uint256"
      }
    ],
    "stateMutability": "view",
    "type": "function"
  },
  {
    "inputs": [
      {
        "internalType": "address",
        "name": "bank",
        "type": "address"
      }
    ],
    "name": "injectLiquidity",
    "outputs": [],
    "stateMutability": "payable",
    "type": "function"
  },
  {
    "inputs": [
      {
        "internalType": "address",
        "name": "",
        "type": "address"
      }
    ],
    "name": "nostroBalances",
    "outputs": [
      {
        "internalType": "uint256",
        "name": "",
        "type": "uint256"
      }
    ],
    "stateMutability": "view",
    "type": "function"
  },
  {
    "inputs": [
      {
        "internalType": "address",
        "name": "settler",
        "type": "address"
      }
    ],
    "name": "revokeSettler",
    "outputs": [],
    "stateMutability": "nonpayable",
    "type": "function"
  },
  {
    "inputs": [
      {
        "internalType": "bytes32",
        "name": "",
        "type": "bytes32"
      }
    ],
    "name": "settlements",
    "outputs": [
      {
        "internalType": "address",
        "name": "sender",
        "type": "address"
      },
      {
        "internalType": "address",
        "name": "receiver",
        "type": "address"
      },
      {
        "internalType": "uint256",
        "name": "amount",
        "type": "uint256"
      },
      {
        "internalType": "bytes32",
        "name": "iso20022Hash",
        "type": "bytes32"
      },
      {
        "internalType": "uint256",
        "name": "timestamp",
        "type": "uint256"
      },
      {
        "internalType": "bool",
        "name": "completed",
        "type": "bool"
      },
      {
        "internalType": "uint8",
        "name": "riskScore",
        "type": "uint8"
      },
      {
        "internalType": "string",
        "name": "currency",
        "type": "string"
      }
    ],
    "stateMutability": "view",
    "type": "function"
  },
  {
    "inputs": [],
    "name": "totalSettlements",
    "outputs": [
      {
        "internalType": "uint256",
        "name": "",
        "type": "uint256"
      }
    ],
    "stateMutability": "view",
    "type": "function"
  },
  {
    "inputs": [],
    "name": "totalVolume",
    "outputs": [
      {
        "internalType": "uint256",
        "name": "",
        "type": "uint256"
      }
    ],
    "stateMutability": "view",
    "type": "function"
  }
]